mcp_applemusic.py
mseep_mcp_applemusic-0.1.9.dist-info/licenses/LICENSE
mseep_mcp_applemusic-0.1.9.dist-info/METADATA
mseep_mcp_applemusic-0.1.9.dist-info/WHEEL
mseep_mcp_applemusic-0.1.9.dist-info/entry_points.txt
mseep_mcp_applemusic-0.1.9.dist-info/top_level.txt
mseep_mcp_applemusic-0.1.9.dist-info/RECORD
