Metadata-Version: 2.4
Name: mseep-mcp-applemusic
Version: 0.1.9
Summary: A simple Apple Music API client for MCP
Author-email: mseep <support@skydeck.ai>
Requires-Python: >=3.13
License-File: LICENSE
Requires-Dist: mcp>=1.2.1
Dynamic: license-file
